cerebrum/__init__.py
cerebrum/clean_today.py
cerebrum/remove_data.py
cerebrum/remove_database.py
cerebrum/crossmodal/__init__.py
cerebrum/crossmodal/cmops.py
cerebrum/crossmodal/mapper.py
cerebrum/crossmodal/utilities.py
cerebrum/hearing/__init__.py
cerebrum/hearing/memops.py
cerebrum/hearing/perception.py
cerebrum/hearing/utilities.py
cerebrum/language/__init__.py
cerebrum/language/analysis.py
cerebrum/language/memops.py
cerebrum/language/utilities.py
cerebrum/neuralnet/__init__.py
cerebrum/neuralnet/trainer.py
cerebrum/neuralnet/utilities.py
cerebrum/neuralnet/weaver.py
cerebrum/neuralnet/datasets/__init__.py
cerebrum/neuralnet/datasets/dataset.py
cerebrum/neuralnet/datasets/sequential.py
cerebrum/neuralnet/datasets/supervised.py
cerebrum/neuralnet/elements/__init__.py
cerebrum/neuralnet/elements/neuron.py
cerebrum/neuralnet/elements/rbm.py
cerebrum/vision/__init__.py
cerebrum/vision/memops.py
cerebrum/vision/perception.py
cerebrum/vision/utilities.py
cerebrum-0.1.81.dist-info/DESCRIPTION.rst
cerebrum-0.1.81.dist-info/METADATA
cerebrum-0.1.81.dist-info/RECORD
cerebrum-0.1.81.dist-info/WHEEL
cerebrum-0.1.81.dist-info/entry_points.txt
cerebrum-0.1.81.dist-info/metadata.json
cerebrum-0.1.81.dist-info/top_level.txt
