Metadata-Version: 2.0
Name: cerebrum
Version: 0.1.81
Summary: Crossmodal Supervised Learning Toolkit using High-Performance Extreme Learning Machines over the audio-visual-textual data
Home-page: https://github.com/mertyildiran/Cerebrum
Author: Mehmet Mert Yildiran
Author-email: mert.yildiran@bil.omu.edu.tr
License: MIT
Keywords: machine learining neural networks artifical intelligence long shor term memory audio video text captions real time
Platform: UNKNOWN
Classifier: Development Status :: 3 - Alpha
Classifier: Intended Audience :: Developers
Classifier: Topic :: Scientific/Engineering :: Artificial Intelligence
Classifier: License :: OSI Approved :: MIT License
Classifier: Programming Language :: Python :: 2.7
Requires-Dist: hpelm
Requires-Dist: imutils
Requires-Dist: pyqtgraph
Requires-Dist: pysrt
Requires-Dist: rethinkdb
